siteforms/__init__.py
siteforms/apps.py
siteforms/base.py
siteforms/fields.py
siteforms/formsets.py
siteforms/metas.py
siteforms/toolbox.py
siteforms/utils.py
siteforms/widgets.py
siteforms/composers/__init__.py
siteforms/composers/base.py
siteforms/composers/bootstrap4.py
siteforms/composers/bootstrap5.py
siteforms/locale/en/LC_MESSAGES/django.po
siteforms/locale/ru/LC_MESSAGES/django.mo
siteforms/locale/ru/LC_MESSAGES/django.po
siteforms/tests/__init__.py
siteforms/tests/conftest.py
siteforms/tests/test_bootstrap4.py
siteforms/tests/test_bootstrap5.py
siteforms/tests/test_common.py
siteforms/tests/test_filtering.py
siteforms/tests/test_nocss.py
siteforms/tests/test_widgets.py
siteforms/tests/datafixtures/bs4_basic_1.html
siteforms/tests/datafixtures/bs5_basic_1.html
siteforms/tests/datafixtures/nocss_basic_1.html
siteforms/tests/testapp/__init__.py
siteforms/tests/testapp/models.py
siteforms/tests/testapp/templates/mywidget.html
django_siteforms-1.1.0.dist-info/AUTHORS
django_siteforms-1.1.0.dist-info/LICENSE
django_siteforms-1.1.0.dist-info/METADATA
django_siteforms-1.1.0.dist-info/SOURCES.txt.py
django_siteforms-1.1.0.dist-info/WHEEL
django_siteforms-1.1.0.dist-info/dependency_links.txt.py
django_siteforms-1.1.0.dist-info/top_level.txt
django_siteforms-1.1.0.dist-info/top_level.txt.py
django_siteforms-1.1.0.dist-info/RECORD
